README.txt
setup.py
docs/HISTORY.txt
docs/INSTALL.txt
docs/LICENSE.GPL
docs/LICENSE.txt
wildcard/__init__.py
wildcard.notrackingsocial.egg-info/PKG-INFO
wildcard.notrackingsocial.egg-info/SOURCES.txt
wildcard.notrackingsocial.egg-info/dependency_links.txt
wildcard.notrackingsocial.egg-info/entry_points.txt
wildcard.notrackingsocial.egg-info/namespace_packages.txt
wildcard.notrackingsocial.egg-info/not-zip-safe
wildcard.notrackingsocial.egg-info/paster_plugins.txt
wildcard.notrackingsocial.egg-info/requires.txt
wildcard.notrackingsocial.egg-info/top_level.txt
wildcard/notrackingsocial/__init__.py
wildcard/notrackingsocial/configure.zcml
wildcard/notrackingsocial/interfaces.py
wildcard/notrackingsocial/tests.py
wildcard/notrackingsocial/browser/.DS_Store
wildcard/notrackingsocial/browser/__init__.py
wildcard/notrackingsocial/browser/configure.zcml
wildcard/notrackingsocial/browser/social.pt
wildcard/notrackingsocial/browser/socialhead.pt
wildcard/notrackingsocial/browser/viewlets.py
wildcard/notrackingsocial/browser/views.py
wildcard/notrackingsocial/browser/resources/facebook.png
wildcard/notrackingsocial/browser/resources/plus.png
wildcard/notrackingsocial/browser/resources/share.png
wildcard/notrackingsocial/browser/resources/social-mail.png
wildcard/notrackingsocial/browser/resources/social-print.png
wildcard/notrackingsocial/browser/resources/twitter.png
wildcard/notrackingsocial/profiles/default/actions.xml
wildcard/notrackingsocial/profiles/default/browserlayer.xml
wildcard/notrackingsocial/profiles/default/controlpanel.xml
wildcard/notrackingsocial/profiles/default/metadata.xml
wildcard/notrackingsocial/profiles/default/registry.xml
wildcard/notrackingsocial/profiles/default/viewlets.xml