Metadata-Version: 1.0
Name: wildcard.notrackingsocial
Version: 1.0a1
Summary: UNKNOWN
Home-page: https://github.com/collective/wildcard.notrackingsocial
Author: Nathan Van Gheem
Author-email: vangheem@gmail.com
License: GPL
Keywords: social plone share buttons
Platform: UNKNOWN
Classifier: Framework :: Plone
Classifier: Programming Language :: Python
